aws_role_credentials-0.6.4.dist-info/RECORD
aws_role_credentials-0.6.4.dist-info/metadata.json
aws_role_credentials-0.6.4.dist-info/WHEEL
aws_role_credentials-0.6.4.dist-info/entry_points.txt
aws_role_credentials-0.6.4.dist-info/DESCRIPTION.rst
aws_role_credentials-0.6.4.dist-info/top_level.txt
aws_role_credentials-0.6.4.dist-info/METADATA
aws_role_credentials/metadata.py
aws_role_credentials/models.py
aws_role_credentials/actions.py
aws_role_credentials/__init__.py
aws_role_credentials/cli.py
