Metadata-Version: 2.0
Name: aws-role-credentials
Version: 0.6.4
Summary: Generates AWS credentials for roles using STS
Home-page: https://github.com/petergillardmoss/aws_role_credentials
Author: Peter Gillard-Moss
Author-email: pgillard@thoughtworks.com
License: ISCL
Keywords: aws_role_credentials
Platform: UNKNOWN
Classifier: Development Status :: 2 - Pre-Alpha
Classifier: Intended Audience :: Developers
Classifier: License :: OSI Approved :: ISC License (ISCL)
Classifier: Natural Language :: English
Classifier: Programming Language :: Python :: 2
Classifier: Programming Language :: Python :: 2.6
Classifier: Programming Language :: Python :: 2.7
Classifier: Programming Language :: Python :: 3
Classifier: Programming Language :: Python :: 3.3
Classifier: Programming Language :: Python :: 3.4
Requires-Dist: boto
Requires-Dist: six
